{
  "OrderID": "10802",
  "OrderDate": "2017-12-29",
  "CustomerName": "Jytte Petersen",
  "Products": [
    {
      "ProductID": "30",
      "Product": "Nord-Ost Matjeshering",
      "Quantity": 25,
      "UnitPrice": 25.89
    },
    {
      "ProductID": "51",
      "Product": "Manjimup Dried Apples",
      "Quantity": 30,
      "UnitPrice": 53.0
    },
    {
      "ProductID": "55",
      "Product": "Pâté chinois",
      "Quantity": 60,
      "UnitPrice": 24.0
    },
    {
      "ProductID": "62",
      "Product": "Tarte au sucre",
      "Quantity": 5,
      "UnitPrice": 49.3
    }
  ]
}