{
  "OrderID": "10315",
  "ShippingDetails": {
    "ShipName": "Island Trading",
    "ShipAddress": "Garden House Crowther Way",
    "ShipCity": "Cowes",
    "ShipRegion": "British Isles",
    "ShipPostalCode": "PO31 7PJ",
    "ShipCountry": "UK"
  },
  "CustomerDetails": {
    "CustomerID": "ISLAT",
    "CustomerName": "Island Trading"
  },
  "EmployeeDetails": {
    "EmployeeName": "Margaret Peacock"
  },
  "ShipperDetails": {
    "ShipperID": "2",
    "ShipperName": "United Package"
  },
  "OrderDetails": {
    "OrderDate": "2016-09-26",
    "ShippedDate": "2016-10-03",
    "Products": [
      {
        "Product": "Sasquatch Ale",
        "Quantity": 14,
        "UnitPrice": 11.2,
        "Total": 156.79999999999998
      },
      {
        "Product": "Outback Lager",
        "Quantity": 30,
        "UnitPrice": 12.0,
        "Total": 360.0
      }
    ],
    "TotalPrice": 516.8
  }
}